pyweft/__init__.py
pyweft/example.py
pyweft-0.1.3.dist-info/METADATA
pyweft-0.1.3.dist-info/WHEEL
pyweft-0.1.3.dist-info/top_level.txt
pyweft-0.1.3.dist-info/RECORD
