Metadata-Version: 2.2
Name: pyweft
Version: 0.1.3
Summary: Python Vortex Lattice
Author-email: Joseph Hobbs <josephrosshobbs@gmail.com>
Classifier: Programming Language :: Python :: 3
Classifier: Operating System :: OS Independent
Requires-Python: >=3.8
